mermod/__init__.py
mermod/_version.py
mermod/io.py
mermod/merging.py
mermod/py.typed
mermod/utils.py
mermod-0.1.0.dist-info/LICENSE
mermod-0.1.0.dist-info/METADATA
mermod-0.1.0.dist-info/WHEEL
mermod-0.1.0.dist-info/top_level.txt
mermod-0.1.0.dist-info/RECORD
