Metadata-Version: 2.2
Name: mermod
Version: 0.1.0
Summary: Package with model merging algorithms
Author: lopusz
License: 
Project-URL: homepage, https://github.com/michal-lopuszynski-tcl/mermod
Classifier: Programming Language :: Python :: 3
Requires-Python: >=3.10
License-File: LICENSE
Requires-Dist: numpy
Requires-Dist: safetensors
Requires-Dist: torch
